{
    "MOLOTOV": {
        "name": "Molotov",
        "description": "Aplica quemado.",
        "usedInCombat": true,
        "usedOutOfCombat": false,
        "habilidades": [
            {
                "actions": 1,
                "damage": 10,
                "effect": "QUEMADO",
                "effectDuration": 3,
                "type": "ACTIVE",
                "target": "ENEMY"
            }
        ]
    },
    "DARDO_ENVENENADO": {
        "name": "Dardo envenenado",
        "description": "Aplica veneno.",
        "usedInCombat": true,
        "usedOutOfCombat": false,
        "habilidades": [
            {
                "actions": 1,
                "damage": 8,
                "effect": "ENVENENADO",
                "effectDuration": 10,
                "type": "ACTIVE",
                "target": "ENEMY"
            }
        ]
    },
    "FLASHBANG": {
        "name": "Flashbang",
        "description": "Paraliza a un enemigo.",
        "usedInCombat": true,
        "usedOutOfCombat": false,
        "habilidades": [
            {
                "actions": 1,
                "damage": 5,
                "effect": "PARALIZADO",
                "effectDuration": 1,
                "type": "ACTIVE",
                "target": "ENEMY"
            }
        ]
    },
    "POTI_HP_MINI": {
        "name": "Poción de salud (mini)",
        "description": "Cura poca HP.",
        "usedInCombat": true,
        "usedOutOfCombat": true,
        "habilidades": [
            {
                "actions": 1,
                "effect": { "diffHealth": 40 },
                "effectDuration": 0,
                "type": "ACTIVE",
                "target": "SELF"
            }
        ]
    },
    "POTI_SP_MINI": {
        "name": "Poción de SP (pequeña)",
        "description": "Restaura SP media.",
        "usedInCombat": true,
        "usedOutOfCombat": true,
        "habilidades": [
            {
                "actions": 1,
                "effect": { "diffSp":30 },
                "effectDuration": 0,
                "type": "ACTIVE",
                "target": "SELF"
            }
        ]
    },
    "NABO": {
        "name": "Nabo",
        "description": "Restaura HP, y no poco.",
        "usedInCombat": true,
        "usedOutOfCombat": true,
        "habilidades": [
            {
                "actions": 1,
                "effect": { "diffHealth": 30 },
                "effectDuration": 0,
                "type": "ACTIVE",
                "target": "SELF"
            }
        ]
    },
    "POTI_HP_GRANDE": {
        "name": "Poción de HP(Grande)",
        "description": "Restaura mucho HP.",
        "usedInCombat": true,
        "usedOutOfCombat": true,
        "habilidades": [
            {
                "actions": 1,
                "effect": { "diffHealth": 150 },
                "effectDuration": 0,
                "type": "ACTIVE",
                "target": "SELF"
            }
        ]
    },
    "MEJUNJE_EXTRAÑO":{
        "name":"Mejunje extraño",
        "description":"Restaura muy poco hambre hambre",
        "usedInCombat": true,
        "usedOutOfCombat": true,
        "habilidades":[
            {
                "actions":1,
                "effect":{},
                "effectDuration":0,
                "type":"ACTIVE",
                "target":"SELF"
            }
        ]
    },
    "RACION_SECA":{
        "name":"Ración seca",
        "description":"Restaura muy poco hambre y SP",
        "usedInCombat": true,
        "usedOutOfCombat": true,
        "habilidades":[
            {
                "actions":1,
                "effect":{},
                "effectDuration":0,
                "type":"ACTIVE",
                "target":"SELF"
            },
            {
                "actions":1,
                "effect":{"diffSP":5},
                "effectDuration":0,
                "type":"ACTIVE",
                "target":"SELF"
            }
        ]
    },
    "RACION_CALIDAD":{
        "name":"Ración de calidad",
        "description":"Restaura poco hambre y SP",
        "usedInCombat": true,
        "usedOutOfCombat": true,
        "habilidades":[
            {
                "actions":1,
                "effect":{},
                "effectDuration":0,
                "type":"ACTIVE",
                "target":"SELF"
            },
            {
                "actions":1,
                "effect":{"diffSP":15},
                "effectDuration":0,
                "type":"ACTIVE",
                "target":"SELF"
            }
        ]
    },
    "RACION_GOURMET":{
        "name":"Ración gourmet",
        "description":"Restaura medio hambre y SP",
        "usedInCombat": true,
        "usedOutOfCombat": true,
        "habilidades":[
            {
                "actions":1,
                "effect":{},
                "effectDuration":0,
                "type":"ACTIVE",
                "target":"SELF"
            },
            {
                "actions":1,
                "effect":{"diffSP":30},
                "effectDuration":0,
                "type":"ACTIVE",
                "target":"SELF"
            }
        ]
    }
}